filesearch_for_win/filesearch.cp312-win_amd64.pyd
filesearch_for_win/filesearch_sdk.dll
filesearch_for_win-0.0.1.dist-info/LICENSE
filesearch_for_win-0.0.1.dist-info/METADATA
filesearch_for_win-0.0.1.dist-info/WHEEL
filesearch_for_win-0.0.1.dist-info/top_level.txt
filesearch_for_win-0.0.1.dist-info/RECORD
