Metadata-Version: 2.1
Name: filesearch_for_win
Version: 0.0.1
Summary: Find files quickly on Windows (requires index)
Author-email: 0cch <author@example.com>
Classifier: Programming Language :: Python :: 3
Classifier: Operating System :: Microsoft :: Windows
Requires-Python: >=3.8
License-File: LICENSE
